{
  "cik": "0001847398",
  "name": "NorthEast Community Bancorp, Inc./MD/",
  "entityType": "operating",
  "sic": "6036",
  "sicDescription": "Savings Institutions, Not Federally Chartered",
  "stateOfIncorporation": "MD",
  "stateOfIncorporationDescription": "MD",
  "fiscalYearEnd": "1231",
  "tickers": [
    "NECB"
  ],
  "exchanges": [
    "Nasdaq"
  ],
  "ein": "000000000",
  "description": "",
  "website": "",
  "investorWebsite": "",
  "category": "<br>Emerging growth company",
  "phone": "(914) 684-2500",
  "flags": "",
  "formerNames": [],
  "filings_count": 174,
  "download_timestamp": "2025-08-02 07:27:00 UTC"
}