{
  "cik": "0001979887",
  "name": "XCHG Ltd",
  "entityType": "other",
  "sic": "3612",
  "sicDescription": "Power, Distribution & Specialty Transformers",
  "stateOfIncorporation": "E9",
  "stateOfIncorporationDescription": "Cayman Islands",
  "fiscalYearEnd": "1231",
  "tickers": [
    "XCH"
  ],
  "exchanges": [
    "Nasdaq"
  ],
  "ein": "000000000",
  "description": "",
  "website": "",
  "investorWebsite": "",
  "category": "Non-accelerated filer<br>Emerging growth company",
  "phone": "008618612790590",
  "flags": "",
  "formerNames": [],
  "filings_count": 49,
  "download_timestamp": "2025-08-02 07:30:58 UTC"
}