{
  "cik": "0001128252",
  "name": "SIPP International Industries, Inc.",
  "entityType": "operating",
  "sic": "3663",
  "sicDescription": "Radio & Tv Broadcasting & Communications Equipment",
  "stateOfIncorporation": "NV",
  "stateOfIncorporationDescription": "NV",
  "fiscalYearEnd": "1231",
  "tickers": [
    "SIPN"
  ],
  "exchanges": [
    "OTC"
  ],
  "ein": "870522115",
  "description": "",
  "website": "",
  "investorWebsite": "",
  "category": "",
  "phone": "(800)524-2526",
  "flags": "",
  "formerNames": [
    {
      "name": "INDUSTRIES INTERNATIONAL INC",
      "from": "2000-12-04T00:00:00.000Z",
      "to": "2004-11-09T00:00:00.000Z"
    }
  ],
  "filings_count": 134,
  "download_timestamp": "2025-08-02 07:07:37 UTC"
}