{
  "cik": "0001759186",
  "name": "Coeptis Therapeutics Holdings, Inc.",
  "entityType": "operating",
  "sic": "2836",
  "sicDescription": "Biological Products, (No Diagnostic Substances)",
  "stateOfIncorporation": "DE",
  "stateOfIncorporationDescription": "DE",
  "fiscalYearEnd": "1231",
  "tickers": [
    "COEP",
    "COEPW"
  ],
  "exchanges": [
    "Nasdaq",
    "Nasdaq"
  ],
  "ein": "981465952",
  "description": "",
  "website": "",
  "investorWebsite": "",
  "category": "Non-accelerated filer<br>Smaller reporting company<br>Emerging growth company",
  "phone": "724-934-6467",
  "flags": "",
  "formerNames": [
    {
      "name": "Bull Horn Holdings Corp.",
      "from": "2019-02-21T05:00:00.000Z",
      "to": "2022-10-28T04:00:00.000Z"
    }
  ],
  "filings_count": 269,
  "download_timestamp": "2025-08-02 07:23:08 UTC"
}