{
  "cik": "0001980994",
  "entityType": "operating",
  "sic": "6221",
  "sicDescription": "Commodity Contracts Brokers & Dealers",
  "ownerOrg": "09 Crypto Assets",
  "insiderTransactionForOwnerExists": 0,
  "insiderTransactionForIssuerExists": 0,
  "name": "iShares Bitcoin Trust ETF",
  "tickers": [
    "IBIT"
  ],
  "exchanges": [
    "Nasdaq"
  ],
  "ein": "000000000",
  "lei": null,
  "description": "",
  "website": "",
  "investorWebsite": "",
  "category": "Non-accelerated filer<br>Emerging growth company",
  "fiscalYearEnd": "1231",
  "stateOfIncorporation": "DE",
  "stateOfIncorporationDescription": "DE",
  "addresses": {
    "mailing": {
      "street1": "C/O ISHARES DELAWARE TRUST SPONSOR, LLC",
      "street2": "400 HOWARD STREET",
      "city": "SAN FRANCISCO",
      "stateOrCountry": "CA",
      "zipCode": "94105",
      "stateOrCountryDescription": "CA",
      "isForeignLocation": 0,
      "foreignStateTerritory": null,
      "country": null,
      "countryCode": null
    },
    "business": {
      "street1": "C/O ISHARES DELAWARE TRUST SPONSOR, LLC",
      "street2": "400 HOWARD STREET",
      "city": "SAN FRANCISCO",
      "stateOrCountry": "CA",
      "zipCode": "94105",
      "stateOrCountryDescription": "CA",
      "isForeignLocation": null,
      "foreignStateTerritory": null,
      "country": null,
      "countryCode": null
    }
  },
  "phone": "415-670-6416",
  "flags": "",
  "formerNames": [
    {
      "name": "iShares Bitcoin Trust",
      "from": "2023-06-15T04:00:00.000Z",
      "to": "2024-07-26T04:00:00.000Z"
    }
  ],
  "filings": {
    "recent": {
      "accessionNumber": [
        "9999999995-25-002418",
        "0001437749-25-024228",
        "0001437749-25-022009",
        "0001437749-25-015853",
        "0001437749-25-015168",
        "0001437749-25-011313",
        "0001437749-25-010167",
        "0001437749-25-006260",
        "0001437749-25-002455",
        "0001437749-24-037076",
        "0001437749-24-033812",
        "0001437749-24-030194",
        "0001437749-24-029619",
        "0001437749-24-025406",
        "0001437749-24-025254",
        "0001437749-24-023611",
        "0001437749-24-020207",
        "0001437749-24-015392",
        "0001437749-24-013419",
        "0001437749-24-012363",
        "9999999995-24-001000",
        "0001437749-24-011116",
        "0001437749-24-006443",
        "0001437749-24-006339",
        "0001437749-24-002911",
        "0001437749-24-002705",
        "9999999995-24-000080",
        "0001437749-24-001125",
        "0001354457-24-000013",
        "0001437749-24-001043",
        "0001437749-24-001046",
        "0001437749-24-000954",
        "0001437749-24-000919",
        "0001437749-24-000917",
        "0000000000-24-000277",
        "0001437749-24-000853",
        "0001437749-24-000788",
        "0001437749-24-000785",
        "0000000000-24-000181",
        "0001437749-23-035560",
        "0001437749-23-035559",
        "0001437749-23-035272",
        "0001437749-23-035270",
        "0000000000-23-013802",
        "0001437749-23-034774",
        "0001437749-23-034772",
        "0001437749-23-033527",
        "0001437749-23-033524",
        "0000000000-23-012441",
        "0001437749-23-028552",
        "0001437749-23-028549",
        "0000000000-23-010822",
        "0001437749-23-017574"
      ],
      "filingDate": [
        "2025-07-31",
        "2025-07-31",
        "2025-07-02",
        "2025-05-09",
        "2025-05-07",
        "2025-04-08",
        "2025-03-31",
        "2025-03-05",
        "2025-02-03",
        "2024-12-10",
        "2024-11-07",
        "2024-09-27",
        "2024-09-19",
        "2024-08-08",
        "2024-08-08",
        "2024-07-26",
        "2024-06-13",
        "2024-05-08",
        "2024-04-26",
        "2024-04-18",
        "2024-04-17",
        "2024-04-05",
        "2024-03-04",
        "2024-03-04",
        "2024-02-02",
        "2024-01-31",
        "2024-01-10",
        "2024-01-10",
        "2024-01-10",
        "2024-01-10",
        "2024-01-09",
        "2024-01-09",
        "2024-01-09",
        "2024-01-09",
        "2024-01-08",
        "2024-01-08",
        "2024-01-08",
        "2024-01-08",
        "2024-01-05",
        "2023-12-29",
        "2023-12-29",
        "2023-12-22",
        "2023-12-22",
        "2023-12-18",
        "2023-12-18",
        "2023-12-18",
        "2023-12-04",
        "2023-12-04",
        "2023-11-13",
        "2023-10-19",
        "2023-10-19",
        "2023-09-29",
        "2023-06-15"
      ],
      "reportDate": [
        "",
        "",
        "",
        "",
        "2025-03-31",
        "2025-04-07",
        "",
        "2024-12-31",
        "",
        "",
        "2024-09-30",
        "",
        "2024-09-16",
        "2024-06-30",
        "",
        "2024-07-26",
        "",
        "2024-03-31",
        "2024-04-23",
        "",
        "",
        "",
        "",
        "2023-12-31",
        "",
        "",
        "",
        "",
        "",
        "",
        "",
        "",
        "",
        "",
        "",
        "",
        "",
        "",
        "",
        "",
        "",
        "",
        "",
        "",
        "",
        "",
        "",
        "",
        "",
        "",
        "",
        "",
        ""
      ],
      "acceptanceDateTime": [
        "2025-08-01T04:15:02.000Z",
        "2025-07-31T21:20:03.000Z",
        "2025-07-02T20:45:56.000Z",
        "2025-05-09T21:27:41.000Z",
        "2025-05-07T21:08:16.000Z",
        "2025-04-08T12:51:08.000Z",
        "2025-03-31T19:52:50.000Z",
        "2025-03-05T19:13:18.000Z",
        "2025-02-03T11:21:01.000Z",
        "2024-12-10T16:28:45.000Z",
        "2024-11-07T16:35:55.000Z",
        "2024-09-27T20:40:22.000Z",
        "2024-09-19T21:26:03.000Z",
        "2024-08-08T16:25:19.000Z",
        "2024-08-08T00:59:49.000Z",
        "2024-07-26T20:43:46.000Z",
        "2024-06-13T20:41:56.000Z",
        "2024-05-08T20:40:01.000Z",
        "2024-04-26T20:09:29.000Z",
        "2024-04-17T23:56:42.000Z",
        "2024-04-18T04:15:19.000Z",
        "2024-04-04T22:10:01.000Z",
        "2024-03-04T22:26:17.000Z",
        "2024-03-02T01:41:01.000Z",
        "2024-02-02T18:20:26.000Z",
        "2024-01-31T22:05:55.000Z",
        "2024-01-11T05:15:22.000Z",
        "2024-01-10T22:14:36.000Z",
        "2024-01-10T21:38:22.000Z",
        "2024-01-10T01:56:44.000Z",
        "2024-01-10T02:05:33.000Z",
        "2024-01-09T16:13:01.000Z",
        "2024-01-09T11:06:41.000Z",
        "2024-01-09T11:06:02.000Z",
        "2024-01-08T23:36:04.000Z",
        "2024-01-08T19:31:45.000Z",
        "2024-01-08T11:10:53.000Z",
        "2024-01-08T11:09:57.000Z",
        "2024-01-05T17:36:07.000Z",
        "2023-12-29T19:34:52.000Z",
        "2023-12-29T19:33:51.000Z",
        "2023-12-22T22:20:30.000Z",
        "2023-12-22T22:19:47.000Z",
        "2023-12-18T23:36:03.000Z",
        "2023-12-18T22:13:04.000Z",
        "2023-12-18T22:10:50.000Z",
        "2023-12-04T22:16:27.000Z",
        "2023-12-04T22:15:05.000Z",
        "2023-11-13T23:01:42.000Z",
        "2023-10-19T10:01:09.000Z",
        "2023-10-19T01:59:47.000Z",
        "2023-09-29T20:30:17.000Z",
        "2023-06-15T20:43:42.000Z"
      ],
      "act": [
        "33",
        "33",
        "33",
        "33",
        "34",
        "34",
        "33",
        "34",
        "33",
        "34",
        "34",
        "34",
        "34",
        "34",
        "33",
        "34",
        "33",
        "34",
        "34",
        "33",
        "33",
        "33",
        "33",
        "34",
        "34",
        "34",
        "33",
        "33",
        "34",
        "33",
        "",
        "",
        "",
        "33",
        "",
        "34",
        "",
        "33",
        "",
        "",
        "33",
        "",
        "33",
        "",
        "",
        "33",
        "",
        "33",
        "",
        "",
        "33",
        "",
        "33"
      ],
      "form": [
        "EFFECT",
        "424B3",
        "POS AM",
        "POS AM",
        "10-Q",
        "8-K",
        "424I",
        "10-K",
        "POS AM",
        "FWP",
        "10-Q",
        "FWP",
        "8-K",
        "10-Q",
        "424B3",
        "8-K",
        "424B3",
        "10-Q",
        "8-K",
        "424B3",
        "EFFECT",
        "POS AM",
        "424B3",
        "10-K",
        "FWP",
        "FWP",
        "EFFECT",
        "424B3",
        "CERT",
        "S-1/A",
        "CORRESP",
        "CORRESP",
        "CORRESP",
        "S-1/A",
        "UPLOAD",
        "8-A12B",
        "CORRESP",
        "S-1/A",
        "UPLOAD",
        "CORRESP",
        "S-1/A",
        "CORRESP",
        "S-1/A",
        "UPLOAD",
        "CORRESP",
        "S-1/A",
        "CORRESP",
        "S-1/A",
        "UPLOAD",
        "CORRESP",
        "S-1/A",
        "UPLOAD",
        "S-1"
      ],
      "fileNumber": [
        "333-272680",
        "333-272680",
        "333-272680",
        "333-272680",
        "001-41914",
        "001-41914",
        "333-272680",
        "001-41914",
        "333-272680",
        "333-272680",
        "001-41914",
        "333-272680",
        "001-41914",
        "001-41914",
        "333-272680",
        "001-41914",
        "333-272680",
        "001-41914",
        "001-41914",
        "333-272680",
        "333-272680",
        "333-272680",
        "333-272680",
        "001-41914",
        "333-272680",
        "333-272680",
        "333-272680",
        "333-272680",
        "001-41914",
        "333-272680",
        "",
        "",
        "",
        "333-272680",
        "333-272680",
        "001-41914",
        "",
        "333-272680",
        "333-272680",
        "",
        "333-272680",
        "",
        "333-272680",
        "333-272680",
        "",
        "333-272680",
        "",
        "333-272680",
        "333-272680",
        "",
        "333-272680",
        "333-272680",
        "333-272680"
      ],
      "filmNumber": [
        "251173485",
        "251172780",
        "251102015",
        "25931825",
        "25922659",
        "25820401",
        "25792901",
        "25710114",
        "25580482",
        "241537566",
        "241434044",
        "241335510",
        "241311265",
        "241187093",
        "241185652",
        "241147654",
        "241041852",
        "24926916",
        "24883726",
        "24852528",
        "24852689",
        "24824269",
        "24716135",
        "24712576",
        "24589946",
        "24583849",
        "24527895",
        "24527263",
        "24527018",
        "24524700",
        "",
        "",
        "",
        "24521661",
        "",
        "24519669",
        "",
        "24518196",
        "",
        "",
        "231527109",
        "",
        "231510839",
        "",
        "",
        "231494661",
        "",
        "231464290",
        "",
        "",
        "231333272",
        "",
        "231018022"
      ],
      "items": [
        ",,",
        "",
        "",
        "",
        "",
        "1.01,9.01",
        "",
        "",
        "",
        "",
        "",
        "",
        "1.01,9.01",
        "",
        "",
        "1.01,9.01",
        "",
        "",
        "5.02",
        "",
        "POS AM,0001437749-24-011116,2024-04-17",
        "",
        "",
        "",
        "",
        "",
        "S-1,,2024-01-10 17:00:00",
        "",
        "",
        "",
        "",
        "",
        "",
        "",
        "",
        "",
        "",
        "",
        "",
        "",
        "",
        "",
        "",
        "",
        "",
        "",
        "",
        "",
        "",
        "",
        "",
        "",
        ""
      ],
      "core_type": [
        "EFFECT",
        "424B3",
        "POS AM",
        "POS AM",
        "XBRL",
        "XBRL",
        "424I",
        "XBRL",
        "POS AM",
        "FWP",
        "XBRL",
        "FWP",
        "XBRL",
        "XBRL",
        "424B3",
        "XBRL",
        "424B3",
        "XBRL",
        "XBRL",
        "424B3",
        "EFFECT",
        "POS AM",
        "424B3",
        "XBRL",
        "FWP",
        "FWP",
        "EFFECT",
        "424B3",
        "CERT",
        "S-1/A",
        "CORRESP",
        "CORRESP",
        "CORRESP",
        "S-1/A",
        "LETTER",
        "8-A12B",
        "CORRESP",
        "S-1/A",
        "LETTER",
        "CORRESP",
        "S-1/A",
        "CORRESP",
        "S-1/A",
        "LETTER",
        "CORRESP",
        "S-1/A",
        "CORRESP",
        "S-1/A",
        "LETTER",
        "CORRESP",
        "S-1/A",
        "LETTER",
        "S-1"
      ],
      "size": [
        1908,
        1371245,
        1893208,
        2090598,
        2681623,
        633860,
        41845,
        3581898,
        1503038,
        668050,
        2446268,
        2676141,
        203555,
        2937535,
        1336924,
        185783,
        1324491,
        2118453,
        164606,
        1317320,
        1824,
        1423874,
        888717,
        2168495,
        563382,
        6048190,
        1811,
        1362052,
        250155,
        1460735,
        23764,
        10045,
        30766,
        1459625,
        43163,
        24245,
        126267,
        1889031,
        52056,
        51575,
        3150122,
        67878,
        2052528,
        62262,
        21159,
        1605838,
        1798597,
        1393176,
        75088,
        64966,
        2953605,
        57360,
        1043287
      ],
      "isXBRL": [
        0,
        0,
        0,
        0,
        1,
        1,
        0,
        1,
        0,
        0,
        1,
        0,
        1,
        1,
        0,
        1,
        0,
        1,
        1,
        0,
        0,
        0,
        0,
        1,
        0,
        0,
        0,
        0,
        0,
        0,
        0,
        0,
        0,
        0,
        0,
        0,
        0,
        0,
        0,
        0,
        0,
        0,
        0,
        0,
        0,
        0,
        0,
        0,
        0,
        0,
        0,
        0,
        0
      ],
      "isInlineXBRL": [
        0,
        0,
        0,
        0,
        1,
        1,
        0,
        1,
        0,
        0,
        1,
        0,
        1,
        1,
        0,
        1,
        0,
        1,
        1,
        0,
        0,
        0,
        0,
        1,
        0,
        0,
        0,
        0,
        0,
        0,
        0,
        0,
        0,
        0,
        0,
        0,
        0,
        0,
        0,
        0,
        0,
        0,
        0,
        0,
        0,
        0,
        0,
        0,
        0,
        0,
        0,
        0,
        0
      ],
      "primaryDocument": [
        "xslEFFECTX01/primary_doc.xml",
        "bit20250731_424b3.htm",
        "bit20250630_posam.htm",
        "bit20250418_posam.htm",
        "bit20250331_10q.htm",
        "bit20250404_8k.htm",
        "bit20250328_424h.htm",
        "bit20241231_10k.htm",
        "bit20250129_posam.htm",
        "bit20241210_fwp.htm",
        "bit20240930c_10q.htm",
        "bit20240925_fwp.htm",
        "bit20240918_8k.htm",
        "bit20240630c_10q.htm",
        "bit20240805_424b3.htm",
        "bit20240726_8k.htm",
        "bit20240606_424b3.htm",
        "bit20240331c_10q.htm",
        "bit20240426_8k.htm",
        "bit20240411_424b3.htm",
        "xslEFFECTX01/primary_doc.xml",
        "bit20240314_posam.htm",
        "bit20240304_424b3.htm",
        "bit20231231_10k.htm",
        "bit20240201_fwp.htm",
        "bit20240130_fwp.htm",
        "xslEFFECTX01/primary_doc.xml",
        "bit20240109_424b3.htm",
        "IBIT_8-A_Cert.pdf",
        "bit20240109_s1a.htm",
        "filename1.htm",
        "filename1.htm",
        "filename1.htm",
        "bit20240108_s1a.htm",
        "filename1.pdf",
        "bit20240108_8a12b.htm",
        "filename1.htm",
        "bit20240106_s1a.htm",
        "filename1.pdf",
        "filename1.htm",
        "bit20231227_s1a.htm",
        "filename1.htm",
        "bit20231221_s1a.htm",
        "filename1.pdf",
        "filename1.htm",
        "bit20231215_s1a.htm",
        "filename1.htm",
        "bit20231201_s1a.htm",
        "filename1.pdf",
        "filename1.htm",
        "bit20231017_s1a.htm",
        "filename1.pdf",
        "bit20230608_s1.htm"
      ],
      "primaryDocDescription": [
        "",
        "FORM 424B3",
        "POS AM",
        "FORM POS AM",
        "FORM 10-Q",
        "FORM 8-K",
        "FORM 424(I)",
        "FORM 10-K",
        "FORM POS AM",
        "FORM FWP",
        "FORM 10-Q",
        "FORM FWP",
        "FORM 8-K",
        "FORM 10-Q",
        "FORM 424B3",
        "FORM 8-K",
        "FORM 424B3",
        "FORM 10-Q",
        "FORM 8-K",
        "FORM 424B3",
        "",
        "FORM POS AM",
        "FORM 424B3",
        "FORM 10-K",
        "FORM FWP",
        "FORM FWP",
        "",
        "FORM 424B3",
        "",
        "FORM S-1/A",
        "",
        "",
        "",
        "",
        "",
        "FORM 8-A12B",
        "",
        "",
        "",
        "",
        "FORM S-1/A",
        "",
        "FORM S-1/A",
        "",
        "",
        "",
        "",
        "",
        "",
        "",
        "FORM S-1/A",
        "",
        "FORM S-1"
      ]
    },
    "files": []
  }
}