{
  "cik": "0002033377",
  "entityType": "other",
  "sic": "7371",
  "sicDescription": "Services-Computer Programming Services",
  "ownerOrg": "06 Technology",
  "insiderTransactionForOwnerExists": 0,
  "insiderTransactionForIssuerExists": 0,
  "name": "Mega Fortune Co Ltd",
  "tickers": [
    "MGRT"
  ],
  "exchanges": [
    "Nasdaq"
  ],
  "ein": "000000000",
  "lei": null,
  "description": "",
  "website": "",
  "investorWebsite": "",
  "category": "",
  "fiscalYearEnd": "0930",
  "stateOfIncorporation": "K3",
  "stateOfIncorporationDescription": "Hong Kong",
  "addresses": {
    "mailing": {
      "street1": "UNIT 327, 3/F, 16 SCIENCE PARK WEST AVEN",
      "street2": "SHATIN, NEW TERRITORIES",
      "city": "HONG KONG",
      "stateOrCountry": "F4",
      "zipCode": "00000",
      "stateOrCountryDescription": "China",
      "isForeignLocation": 0,
      "foreignStateTerritory": null,
      "country": null,
      "countryCode": null
    },
    "business": {
      "street1": "UNIT 327, 3/F, 16 SCIENCE PARK WEST AVEN",
      "street2": "SHATIN, NEW TERRITORIES",
      "city": "HONG KONG",
      "stateOrCountry": "F4",
      "zipCode": "00000",
      "stateOrCountryDescription": "China",
      "isForeignLocation": null,
      "foreignStateTerritory": null,
      "country": null,
      "countryCode": null
    }
  },
  "phone": "852 5627 5338",
  "flags": "",
  "formerNames": [],
  "filings": {
    "recent": {
      "accessionNumber": [
        "0001213900-25-065695",
        "0001213900-25-064701",
        "0001354457-25-000675",
        "0001213900-25-064282",
        "9999999995-25-002077",
        "0001213900-25-059422",
        "0001213900-25-039080",
        "0001213900-24-093930",
        "0001213900-24-078489",
        "0001213900-24-067177"
      ],
      "filingDate": [
        "2025-07-18",
        "2025-07-16",
        "2025-07-15",
        "2025-07-15",
        "2025-06-30",
        "2025-06-30",
        "2025-05-02",
        "2024-11-04",
        "2024-09-13",
        "2024-08-09"
      ],
      "reportDate": [
        "2025-07-18",
        "",
        "",
        "",
        "",
        "",
        "",
        "",
        "",
        ""
      ],
      "acceptanceDateTime": [
        "2025-07-18T20:30:33.000Z",
        "2025-07-16T20:21:29.000Z",
        "2025-07-15T20:40:32.000Z",
        "2025-07-15T20:30:02.000Z",
        "2025-07-01T04:15:11.000Z",
        "2025-06-30T16:18:16.000Z",
        "2025-05-02T19:36:43.000Z",
        "2024-11-04T17:48:49.000Z",
        "2024-09-13T19:08:37.000Z",
        "2024-08-09T20:36:38.000Z"
      ],
      "act": [
        "34",
        "33",
        "34",
        "34",
        "33",
        "33",
        "33",
        "33",
        "33",
        "33"
      ],
      "form": [
        "6-K",
        "424B4",
        "CERT",
        "8-A12B",
        "EFFECT",
        "F-1/A",
        "F-1/A",
        "F-1",
        "DRS/A",
        "DRS"
      ],
      "fileNumber": [
        "001-42751",
        "333-282977",
        "001-42751",
        "001-42751",
        "333-282977",
        "333-282977",
        "333-282977",
        "333-282977",
        "377-07373",
        "377-07373"
      ],
      "filmNumber": [
        "251134843",
        "251127689",
        "251125240",
        "251125120",
        "251094036",
        "251090189",
        "25908096",
        "241421972",
        "241297472",
        "241193400"
      ],
      "items": [
        "",
        "",
        "",
        "",
        ",,",
        "",
        "",
        "",
        "",
        ""
      ],
      "core_type": [
        "6-K",
        "424B4",
        "CERT",
        "8-A12B",
        "EFFECT",
        "F-1/A",
        "F-1/A",
        "F-1",
        "DRS/A",
        "DRS"
      ],
      "size": [
        302827,
        7741365,
        123374,
        16180,
        1827,
        8954625,
        8111554,
        11245801,
        7459376,
        7413237
      ],
      "isXBRL": [
        0,
        0,
        0,
        0,
        0,
        0,
        0,
        0,
        0,
        0
      ],
      "isInlineXBRL": [
        0,
        0,
        0,
        0,
        0,
        0,
        0,
        0,
        0,
        0
      ],
      "primaryDocument": [
        "ea0249541-6k_mega.htm",
        "ea0209090-09.htm",
        "8A_CERT_MGRT.pdf",
        "ea0248968-8a12b_megafor.htm",
        "xslEFFECTX01/primary_doc.xml",
        "ea0209090-08.htm",
        "ea0209090-07.htm",
        "ea0209090-05.htm",
        "filename1.htm",
        "filename1.htm"
      ],
      "primaryDocDescription": [
        "REPORT OF FOREIGN PRIVATE ISSUER",
        "PROSPECTUS",
        "",
        "FOR REGISTRATION OF CERTAIN CLASSES",
        "",
        "REGISTRATION STATEMENT",
        "REGISTRATION STATEMENT",
        "REGISTRATION STATEMENT",
        "",
        ""
      ]
    },
    "files": []
  }
}