{
  "cik": "0001313938",
  "name": "Sibannac, Inc.",
  "entityType": "operating",
  "sic": "2834",
  "sicDescription": "Pharmaceutical Preparations",
  "stateOfIncorporation": "NV",
  "stateOfIncorporationDescription": "NV",
  "fiscalYearEnd": "0831",
  "tickers": [
    "SNNC"
  ],
  "exchanges": [
    "OTC"
  ],
  "ein": "330903494",
  "description": "",
  "website": "",
  "investorWebsite": "",
  "category": "Smaller reporting company",
  "phone": "480-498-8300",
  "flags": "",
  "formerNames": [
    {
      "name": "Sibannic, Inc.",
      "from": "2015-03-11T00:00:00.000Z",
      "to": "2015-03-12T00:00:00.000Z"
    },
    {
      "name": "Naprodis, Inc.",
      "from": "2005-01-12T00:00:00.000Z",
      "to": "2015-01-20T00:00:00.000Z"
    }
  ],
  "filings_count": 105,
  "download_timestamp": "2025-08-02 07:10:15 UTC"
}