{
  "cik": "0001996210",
  "name": "BLUM HOLDINGS, INC.",
  "entityType": "operating",
  "sic": "5900",
  "sicDescription": "Retail-Miscellaneous Retail",
  "stateOfIncorporation": "",
  "stateOfIncorporationDescription": "",
  "fiscalYearEnd": "1231",
  "tickers": [
    "BLMH"
  ],
  "exchanges": [
    "OTC"
  ],
  "ein": "933735199",
  "description": "",
  "website": "",
  "investorWebsite": "",
  "category": "Non-accelerated filer<br>Smaller reporting company",
  "phone": "3238410046",
  "flags": "",
  "formerNames": [],
  "filings_count": 85,
  "download_timestamp": "2025-08-02 07:31:27 UTC"
}