{
  "cik": "0001602409",
  "name": "FingerMotion, Inc.",
  "entityType": "operating",
  "sic": "7372",
  "sicDescription": "Services-Prepackaged Software",
  "stateOfIncorporation": "DE",
  "stateOfIncorporationDescription": "DE",
  "fiscalYearEnd": "0228",
  "tickers": [
    "FNGR"
  ],
  "exchanges": [
    "Nasdaq"
  ],
  "ein": "464600326",
  "description": "",
  "website": "",
  "investorWebsite": "",
  "category": "Non-accelerated filer<br>Smaller reporting company",
  "phone": "(347) 349-5339",
  "flags": "",
  "formerNames": [
    {
      "name": "Property Management Corp of America",
      "from": "2014-03-14T04:00:00.000Z",
      "to": "2017-07-18T04:00:00.000Z"
    }
  ],
  "filings_count": 290,
  "download_timestamp": "2025-08-02 07:18:19 UTC"
}