{
  "cik": "0000923796",
  "name": "GEO GROUP INC",
  "entityType": "operating",
  "sic": "1520",
  "sicDescription": "General Bldg Contractors - Residential Bldgs",
  "stateOfIncorporation": "FL",
  "stateOfIncorporationDescription": "FL",
  "fiscalYearEnd": "1231",
  "tickers": [
    "GEO"
  ],
  "exchanges": [
    "NYSE"
  ],
  "ein": "650043078",
  "description": "",
  "website": "",
  "investorWebsite": "",
  "category": "Large accelerated filer",
  "phone": "561-893-0101",
  "flags": "",
  "formerNames": [
    {
      "name": "WACKENHUT CORRECTIONS CORP",
      "from": "1996-06-07T04:00:00.000Z",
      "to": "2003-11-18T05:00:00.000Z"
    }
  ],
  "filings_count": 1002,
  "download_timestamp": "2025-08-02 07:03:43 UTC"
}