{
  "cik": "0001668438",
  "name": "Integrated Media Technology Ltd",
  "entityType": "other",
  "sic": "3651",
  "sicDescription": "Household Audio & Video Equipment",
  "stateOfIncorporation": "C3",
  "stateOfIncorporationDescription": "Australia",
  "fiscalYearEnd": "1231",
  "tickers": [
    "IMTE"
  ],
  "exchanges": [
    "Nasdaq"
  ],
  "ein": "000000000",
  "description": "",
  "website": "",
  "investorWebsite": "",
  "category": "Non-accelerated filer<br>Emerging growth company",
  "phone": "61873246018",
  "flags": "",
  "formerNames": [],
  "filings_count": 265,
  "download_timestamp": "2025-08-02 07:20:14 UTC"
}