{
  "cik": "0001941506",
  "name": "ZJK Industrial Co., Ltd.",
  "entityType": "other",
  "sic": "3452",
  "sicDescription": "Bolts, Nuts, Screws, Rivets & Washers",
  "stateOfIncorporation": "E9",
  "stateOfIncorporationDescription": "Cayman Islands",
  "fiscalYearEnd": "1231",
  "tickers": [
    "ZJK"
  ],
  "exchanges": [
    "Nasdaq"
  ],
  "ein": "000000000",
  "description": "",
  "website": "",
  "investorWebsite": "",
  "category": "Non-accelerated filer<br>Emerging growth company",
  "phone": "8613682653192",
  "flags": "",
  "formerNames": [],
  "filings_count": 43,
  "download_timestamp": "2025-08-02 07:29:58 UTC"
}