{
  "cik": "0001031093",
  "name": "SILVER BULL RESOURCES, INC.",
  "entityType": "operating",
  "sic": "1000",
  "sicDescription": "Metal Mining",
  "stateOfIncorporation": "NV",
  "stateOfIncorporationDescription": "NV",
  "fiscalYearEnd": "1031",
  "tickers": [
    "SVBL"
  ],
  "exchanges": [
    "OTC"
  ],
  "ein": "911766677",
  "description": "",
  "website": "",
  "investorWebsite": "",
  "category": "Non-accelerated filer<br>Smaller reporting company",
  "phone": "604-687-5800",
  "flags": "",
  "formerNames": [
    {
      "name": "METALLINE MINING CO",
      "from": "1999-10-15T04:00:00.000Z",
      "to": "2011-05-18T04:00:00.000Z"
    }
  ],
  "filings_count": 708,
  "download_timestamp": "2025-08-02 07:05:08 UTC"
}