{
  "cik": "0001468608",
  "entityType": "other",
  "sic": "",
  "sicDescription": "",
  "ownerOrg": null,
  "insiderTransactionForOwnerExists": 0,
  "insiderTransactionForIssuerExists": 0,
  "name": "Vodacom Group Ltd / ADR",
  "tickers": [
    "VDMCY",
    "VODAF"
  ],
  "exchanges": [
    "OTC",
    "OTC"
  ],
  "ein": "000000000",
  "lei": null,
  "description": "",
  "website": "",
  "investorWebsite": "",
  "category": "",
  "fiscalYearEnd": null,
  "stateOfIncorporation": "",
  "stateOfIncorporationDescription": "",
  "addresses": {
    "mailing": {
      "street1": "120 BROADWAY",
      "street2": "32ND FLOOR",
      "city": "NEW YORK",
      "stateOrCountry": "NY",
      "zipCode": "10271",
      "stateOrCountryDescription": "NY",
      "isForeignLocation": null,
      "foreignStateTerritory": null,
      "country": null,
      "countryCode": null
    },
    "business": {
      "street1": "120 BROADWAY",
      "street2": "32ND FLOOR",
      "city": "NEW YORK",
      "stateOrCountry": "NY",
      "zipCode": "10271",
      "stateOrCountryDescription": "NY",
      "isForeignLocation": null,
      "foreignStateTerritory": null,
      "country": null,
      "countryCode": null
    }
  },
  "phone": "212-238-3010",
  "flags": "",
  "formerNames": [],
  "filings": {
    "recent": {
      "accessionNumber": [
        "9999999995-23-002943",
        "0001193805-23-001318",
        "9999999995-13-001991",
        "0001193805-13-001178",
        "0001193805-13-000399",
        "0001193805-13-000148",
        "0001019155-09-000648"
      ],
      "filingDate": [
        "2023-10-05",
        "2023-09-25",
        "2013-07-02",
        "2013-06-25",
        "2013-02-13",
        "2013-01-30",
        "2009-07-20"
      ],
      "reportDate": [
        "",
        "",
        "",
        "",
        "",
        "",
        ""
      ],
      "acceptanceDateTime": [
        "2023-10-06T00:15:06.000Z",
        "2023-09-25T12:55:30.000Z",
        "2013-07-03T00:15:12.000Z",
        "2013-06-25T13:49:41.000Z",
        "2013-02-13T16:40:27.000Z",
        "2013-01-30T17:03:50.000Z",
        "2009-07-20T16:31:47.000Z"
      ],
      "act": [
        "33",
        "33",
        "33",
        "33",
        "33",
        "33",
        "33"
      ],
      "form": [
        "EFFECT",
        "F-6",
        "EFFECT",
        "F-6",
        "F-6EF",
        "F-6EF",
        "F-6EF"
      ],
      "fileNumber": [
        "333-274678",
        "333-274678",
        "333-189570",
        "333-189570",
        "333-186661",
        "333-186314",
        "333-160694"
      ],
      "filmNumber": [
        "231312510",
        "231274413",
        "13950912",
        "13931544",
        "13603854",
        "13559797",
        "09953330"
      ],
      "items": [
        "F-6,,2023-10-05 09:00:00",
        "",
        "F-6,,2013-07-02 09:00:00",
        "",
        "",
        "",
        ""
      ],
      "core_type": [
        "EFFECT",
        "F-6",
        "EFFECT",
        "F-6",
        "F-6EF",
        "F-6EF",
        "F-6EF"
      ],
      "size": [
        1570,
        442589,
        1569,
        654471,
        190078,
        206614,
        78176
      ],
      "isXBRL": [
        0,
        0,
        0,
        0,
        0,
        0,
        0
      ],
      "isInlineXBRL": [
        0,
        0,
        0,
        0,
        0,
        0,
        0
      ],
      "primaryDocument": [
        "xslEFFECTX01/primary_doc.xml",
        "e618954_f6-vodacom.htm",
        "xslEFFECTX01/primary_doc.xml",
        "e611046_f6-vodacom.htm",
        "e610543_f6ef-vodacom.htm",
        "e610415_f6ef-vodacom.htm",
        "vodacomunsponsoredformf6.htm"
      ],
      "primaryDocDescription": [
        "",
        "",
        "",
        "",
        "",
        "",
        "FORM F-6"
      ]
    },
    "files": []
  }
}