{
  "cik": "0001848763",
  "name": "ReNew Energy Global plc",
  "entityType": "other",
  "sic": "4911",
  "sicDescription": "Electric Services",
  "stateOfIncorporation": "K7",
  "stateOfIncorporationDescription": "India",
  "fiscalYearEnd": "0331",
  "tickers": [
    "RNW",
    "RNWWW"
  ],
  "exchanges": [
    "Nasdaq",
    "Nasdaq"
  ],
  "ein": "000000000",
  "description": "",
  "website": "",
  "investorWebsite": "",
  "category": "Accelerated filer",
  "phone": "91 99710 95748",
  "flags": "",
  "formerNames": [
    {
      "name": "ReNew Energy Global Ltd",
      "from": "2021-03-02T05:00:00.000Z",
      "to": "2021-05-18T04:00:00.000Z"
    }
  ],
  "filings_count": 192,
  "download_timestamp": "2025-08-02 07:27:04 UTC"
}