{
  "cik": "0002044241",
  "name": "TryHard Holdings Ltd",
  "entityType": "other",
  "sic": "7990",
  "sicDescription": "Services-Miscellaneous Amusement & Recreation",
  "stateOfIncorporation": "E9",
  "stateOfIncorporationDescription": "Cayman Islands",
  "fiscalYearEnd": "0630",
  "tickers": [
    "THH"
  ],
  "exchanges": [
    null
  ],
  "ein": "000000000",
  "description": "",
  "website": "",
  "investorWebsite": "",
  "category": "",
  "phone": "81 06-4708-6470",
  "flags": "",
  "formerNames": [],
  "filings_count": 5,
  "download_timestamp": "2025-08-02 07:33:06 UTC"
}