{
  "cik": "0001967656",
  "name": "PFS Bancorp, Inc.",
  "entityType": "operating",
  "sic": "6036",
  "sicDescription": "Savings Institutions, Not Federally Chartered",
  "stateOfIncorporation": "",
  "stateOfIncorporationDescription": "",
  "fiscalYearEnd": "1231",
  "tickers": [
    "PFSB"
  ],
  "exchanges": [
    "OTC"
  ],
  "ein": "922956265",
  "description": "",
  "website": "",
  "investorWebsite": "",
  "category": "<br>Emerging growth company",
  "phone": "815-223-4300",
  "flags": "",
  "formerNames": [],
  "filings_count": 48,
  "download_timestamp": "2025-08-02 07:30:39 UTC"
}