{
  "cik": "0001356914",
  "entityType": "other",
  "sic": "8090",
  "sicDescription": "Services-Misc Health & Allied Services, NEC",
  "ownerOrg": "08 Industrial Applications and Services",
  "insiderTransactionForOwnerExists": 0,
  "insiderTransactionForIssuerExists": 0,
  "name": "ECOPLUS INC",
  "tickers": [
    "ECPL"
  ],
  "exchanges": [
    "OTC"
  ],
  "ein": "000000000",
  "lei": null,
  "description": "",
  "website": "",
  "investorWebsite": "",
  "category": "",
  "fiscalYearEnd": null,
  "stateOfIncorporation": "WY",
  "stateOfIncorporationDescription": "WY",
  "addresses": {
    "mailing": {
      "street1": "120 WASHINGTON ST.",
      "street2": null,
      "city": "SALEM",
      "stateOrCountry": "MA",
      "zipCode": "01970",
      "stateOrCountryDescription": "MA",
      "isForeignLocation": null,
      "foreignStateTerritory": null,
      "country": null,
      "countryCode": null
    },
    "business": {
      "street1": "120 WASHINGTON ST.",
      "street2": null,
      "city": "SALEM",
      "stateOrCountry": "MA",
      "zipCode": "01970",
      "stateOrCountryDescription": "MA",
      "isForeignLocation": null,
      "foreignStateTerritory": null,
      "country": null,
      "countryCode": null
    }
  },
  "phone": "855-955-3275",
  "flags": "",
  "formerNames": [],
  "filings": {
    "recent": {
      "accessionNumber": [
        "0001393905-25-000046",
        "0001393905-24-000265",
        "9999999997-08-007063",
        "9999999997-06-033096",
        "9999999997-06-010501"
      ],
      "filingDate": [
        "2025-02-07",
        "2024-07-23",
        "2008-02-19",
        "2006-07-25",
        "2006-03-10"
      ],
      "reportDate": [
        "",
        "",
        "",
        "",
        ""
      ],
      "acceptanceDateTime": [
        "2025-02-07T14:34:40.000Z",
        "2024-07-23T16:00:55.000Z",
        "2008-02-22T12:56:15.000Z",
        "2006-08-03T10:10:56.000Z",
        "2006-03-23T15:01:49.000Z"
      ],
      "act": [
        "33",
        "33",
        "34",
        "34",
        "34"
      ],
      "form": [
        "1-A/A",
        "1-A",
        "REGDEX",
        "REGDEX",
        "REGDEX"
      ],
      "fileNumber": [
        "024-12470",
        "024-12470",
        "021-87509",
        "021-87509",
        "021-87509"
      ],
      "filmNumber": [
        "25601069",
        "241134456",
        "08040182",
        "06042696",
        "06027435"
      ],
      "items": [
        "",
        "",
        "04",
        "04",
        "46"
      ],
      "core_type": [
        "1-A/A",
        "1-A",
        "REGDEX",
        "REGDEX",
        "REGDEX"
      ],
      "size": [
        853917,
        3625364,
        1586,
        1586,
        1586
      ],
      "isXBRL": [
        0,
        0,
        0,
        0,
        0
      ],
      "isInlineXBRL": [
        0,
        0,
        0,
        0,
        0
      ],
      "primaryDocument": [
        "xsl1-A_X01/primary_doc.xml",
        "xsl1-A_X01/primary_doc.xml",
        "9999999997-08-007063.paper",
        "9999999997-06-033096.paper",
        "9999999997-06-010501.paper"
      ],
      "primaryDocDescription": [
        "",
        "",
        "AUTO-GENERATED PAPER DOCUMENT",
        "AUTO-GENERATED PAPER DOCUMENT",
        "AUTO-GENERATED PAPER DOCUMENT"
      ]
    },
    "files": []
  }
}