{
  "cik": "0001914805",
  "name": "CBL International Ltd",
  "entityType": "other",
  "sic": "5172",
  "sicDescription": "Wholesale-Petroleum & Petroleum Products (No Bulk Stations)",
  "stateOfIncorporation": "E9",
  "stateOfIncorporationDescription": "Cayman Islands",
  "fiscalYearEnd": "1231",
  "tickers": [
    "BANL"
  ],
  "exchanges": [
    "Nasdaq"
  ],
  "ein": "000000000",
  "description": "",
  "website": "",
  "investorWebsite": "",
  "category": "Non-accelerated filer<br>Emerging growth company",
  "phone": "603 2706 8280",
  "flags": "",
  "formerNames": [],
  "filings_count": 98,
  "download_timestamp": "2025-08-02 07:29:25 UTC"
}