{
  "cik": "0001108645",
  "name": "Correlate Energy Corp.",
  "entityType": "operating",
  "sic": "8711",
  "sicDescription": "Services-Engineering Services",
  "stateOfIncorporation": "NV",
  "stateOfIncorporationDescription": "NV",
  "fiscalYearEnd": "1231",
  "tickers": [
    "CIPI"
  ],
  "exchanges": [
    "OTC"
  ],
  "ein": "844250492",
  "description": "",
  "website": "",
  "investorWebsite": "",
  "category": "Non-accelerated filer<br>Smaller reporting company",
  "phone": "855-264-4060",
  "flags": "",
  "formerNames": [
    {
      "name": "Correlate Infrastructure Partners, Inc.",
      "from": "2022-04-14T00:00:00.000Z",
      "to": "2023-05-16T00:00:00.000Z"
    },
    {
      "name": "TRICCAR INC.",
      "from": "2021-07-09T00:00:00.000Z",
      "to": "2022-04-01T00:00:00.000Z"
    },
    {
      "name": "FRONTIER OILFIELD SERVICES INC",
      "from": "2012-02-28T00:00:00.000Z",
      "to": "2021-06-01T00:00:00.000Z"
    },
    {
      "name": "TBX RESOURCES INC",
      "from": "2000-03-10T00:00:00.000Z",
      "to": "2011-11-09T00:00:00.000Z"
    }
  ],
  "filings_count": 292,
  "download_timestamp": "2025-08-02 07:07:12 UTC"
}