{
  "cik": "0001160106",
  "name": "Lloyds Banking Group plc",
  "entityType": "other",
  "sic": "6029",
  "sicDescription": "Commercial Banks, NEC",
  "stateOfIncorporation": "X0",
  "stateOfIncorporationDescription": "United Kingdom",
  "fiscalYearEnd": null,
  "tickers": [
    "LYG",
    "LLDTF",
    "LLOBF"
  ],
  "exchanges": [
    "NYSE",
    "OTC",
    "OTC"
  ],
  "ein": "000000000",
  "description": "",
  "website": "",
  "investorWebsite": "",
  "category": "Large accelerated filer",
  "phone": "44 0 20 7626 1500",
  "flags": "",
  "formerNames": [
    {
      "name": "LLOYDS TSB GROUP PLC",
      "from": "2002-02-25T05:00:00.000Z",
      "to": "2009-01-20T05:00:00.000Z"
    }
  ],
  "filings_count": 1002,
  "download_timestamp": "2025-08-02 07:08:13 UTC"
}