{
  "cik": "0001999157",
  "entityType": "other",
  "sic": "",
  "sicDescription": "",
  "ownerOrg": "International Corp Fin",
  "insiderTransactionForOwnerExists": 0,
  "insiderTransactionForIssuerExists": 0,
  "name": "Energean PLC/ADR",
  "tickers": [
    "ENOGY",
    "EERGF"
  ],
  "exchanges": [
    "OTC",
    "OTC"
  ],
  "ein": "000000000",
  "lei": null,
  "description": "",
  "website": "",
  "investorWebsite": "",
  "category": "",
  "fiscalYearEnd": "1231",
  "stateOfIncorporation": "X0",
  "stateOfIncorporationDescription": "United Kingdom",
  "addresses": {
    "mailing": {
      "street1": "C/O CITIBANK, N.A.",
      "street2": "388 GREENWICH ST",
      "city": "NEW YORK",
      "stateOrCountry": "NY",
      "zipCode": "10013",
      "stateOrCountryDescription": "NY",
      "isForeignLocation": null,
      "foreignStateTerritory": null,
      "country": null,
      "countryCode": null
    },
    "business": {
      "street1": "3RD FLOOR, ACCURIST HOUSE",
      "street2": "44 BAKER STREET",
      "city": "LONDON",
      "stateOrCountry": "X0",
      "zipCode": "W1U 7AL",
      "stateOrCountryDescription": "United Kingdom",
      "isForeignLocation": null,
      "foreignStateTerritory": null,
      "country": null,
      "countryCode": null
    }
  },
  "phone": "212-816-6638",
  "flags": "",
  "formerNames": [],
  "filings": {
    "recent": {
      "accessionNumber": [
        "0001178913-25-000460",
        "0001178913-24-000326",
        "0001193805-23-001518",
        "0001193805-23-001459"
      ],
      "filingDate": [
        "2025-02-13",
        "2024-01-31",
        "2023-11-20",
        "2023-10-31"
      ],
      "reportDate": [
        "",
        "",
        "",
        ""
      ],
      "acceptanceDateTime": [
        "2025-02-13T17:02:00.000Z",
        "2024-01-31T11:10:29.000Z",
        "2023-11-20T22:30:49.000Z",
        "2023-10-31T14:51:23.000Z"
      ],
      "act": [
        "34",
        "34",
        "33",
        "33"
      ],
      "form": [
        "SCHEDULE 13G",
        "SC 13G",
        "F-6EF",
        "F-6EF"
      ],
      "fileNumber": [
        "005-94316",
        "005-94316",
        "333-275672",
        "333-275225"
      ],
      "filmNumber": [
        "25618484",
        "24580519",
        "231423760",
        "231362709"
      ],
      "items": [
        "",
        "",
        "",
        ""
      ],
      "core_type": [
        "SCHEDULE 13G",
        "SC 13G",
        "F-6EF",
        "F-6EF"
      ],
      "size": [
        10697,
        43410,
        139629,
        140007
      ],
      "isXBRL": [
        0,
        0,
        0,
        0
      ],
      "isInlineXBRL": [
        0,
        0,
        0,
        0
      ],
      "primaryDocument": [
        "xslSCHEDULE_13G_X01/primary_doc.xml",
        "zk2430852.htm",
        "e619075_f6ef-energean.htm",
        "e619037_f6ef-energean.htm"
      ],
      "primaryDocDescription": [
        "",
        "SC13G",
        "",
        ""
      ]
    },
    "files": []
  }
}