{
  "cik": "0001483646",
  "name": "BLACKSTAR ENTERPRISE GROUP, INC.",
  "entityType": "operating",
  "sic": "6199",
  "sicDescription": "Finance Services",
  "stateOfIncorporation": "DE",
  "stateOfIncorporationDescription": "DE",
  "fiscalYearEnd": "1231",
  "tickers": [
    "BEGI"
  ],
  "exchanges": [
    "OTC"
  ],
  "ein": "271120628",
  "description": "",
  "website": "",
  "investorWebsite": "",
  "category": "Non-accelerated filer<br>Smaller reporting company<br>Emerging growth company",
  "phone": "303-500-3210",
  "flags": "",
  "formerNames": [
    {
      "name": "BLACKSTAR ENERGY GROUP, INC.",
      "from": "2010-02-12T05:00:00.000Z",
      "to": "2016-12-29T05:00:00.000Z"
    }
  ],
  "filings_count": 209,
  "download_timestamp": "2025-08-02 07:14:33 UTC"
}