{
  "cik": "0001173313",
  "name": "ABVC BIOPHARMA, INC.",
  "entityType": "operating",
  "sic": "2834",
  "sicDescription": "Pharmaceutical Preparations",
  "stateOfIncorporation": "NV",
  "stateOfIncorporationDescription": "NV",
  "fiscalYearEnd": "1231",
  "tickers": [
    "ABVC"
  ],
  "exchanges": [
    "Nasdaq"
  ],
  "ein": "260014658",
  "description": "",
  "website": "",
  "investorWebsite": "",
  "category": "Non-accelerated filer<br>Smaller reporting company",
  "phone": "510-668-0881",
  "flags": "",
  "formerNames": [
    {
      "name": "American BriVision (Holding) Corp",
      "from": "2016-01-29T05:00:00.000Z",
      "to": "2021-04-08T04:00:00.000Z"
    },
    {
      "name": "METU BRANDS, INC.",
      "from": "2015-09-08T04:00:00.000Z",
      "to": "2016-01-08T05:00:00.000Z"
    },
    {
      "name": "Ecology Coatings, Inc.",
      "from": "2008-08-22T04:00:00.000Z",
      "to": "2015-09-02T04:00:00.000Z"
    },
    {
      "name": "ECOLOGY COATINGS, INC.",
      "from": "2008-08-22T04:00:00.000Z",
      "to": "2015-09-02T04:00:00.000Z"
    },
    {
      "name": "OCIS CORP",
      "from": "2002-06-28T04:00:00.000Z",
      "to": "2007-06-13T04:00:00.000Z"
    }
  ],
  "filings_count": 754,
  "download_timestamp": "2025-08-02 07:08:31 UTC"
}