{
  "cik": "0001618673",
  "name": "Performance Food Group Co",
  "entityType": "operating",
  "sic": "5141",
  "sicDescription": "Wholesale-Groceries, General Line",
  "stateOfIncorporation": "DE",
  "stateOfIncorporationDescription": "DE",
  "fiscalYearEnd": "0628",
  "tickers": [
    "PFGC"
  ],
  "exchanges": [
    "NYSE"
  ],
  "ein": "431983182",
  "description": "",
  "website": "",
  "investorWebsite": "",
  "category": "Large accelerated filer",
  "phone": "(804) 484-7700",
  "flags": "",
  "formerNames": [],
  "filings_count": 955,
  "download_timestamp": "2025-08-02 07:18:51 UTC"
}