{
  "cik": "0001394638",
  "name": "Driveitaway Holdings, Inc.",
  "entityType": "operating",
  "sic": "8200",
  "sicDescription": "Services-Educational Services",
  "stateOfIncorporation": "DE",
  "stateOfIncorporationDescription": "DE",
  "fiscalYearEnd": "0930",
  "tickers": [
    "DWAY"
  ],
  "exchanges": [
    "OTC"
  ],
  "ein": "204456503",
  "description": "",
  "website": "",
  "investorWebsite": "",
  "category": "Non-accelerated filer<br>Smaller reporting company",
  "phone": "904-824-3133",
  "flags": "",
  "formerNames": [
    {
      "name": "CREATIVE LEARNING Corp",
      "from": "2010-08-04T04:00:00.000Z",
      "to": "2022-04-04T04:00:00.000Z"
    },
    {
      "name": "B2 HEALTH, INC.",
      "from": "2007-09-11T04:00:00.000Z",
      "to": "2010-07-30T04:00:00.000Z"
    }
  ],
  "filings_count": 363,
  "download_timestamp": "2025-08-02 07:12:09 UTC"
}