{
  "cik": "0002037916",
  "name": "GEBE Environmental Technology Ltd",
  "entityType": "other",
  "sic": "0800",
  "sicDescription": "Forestry",
  "stateOfIncorporation": "",
  "stateOfIncorporationDescription": "",
  "fiscalYearEnd": null,
  "tickers": [],
  "exchanges": [],
  "ein": "000000000",
  "description": "",
  "website": "",
  "investorWebsite": "",
  "category": "",
  "phone": "65 9735 3700",
  "flags": "",
  "formerNames": [],
  "filings_count": 6,
  "download_timestamp": "2025-08-02 07:32:55 UTC"
}