{
  "cik": "0001704720",
  "name": "Cannae Holdings, Inc.",
  "entityType": "operating",
  "sic": "5810",
  "sicDescription": "Retail-Eating & Drinking Places",
  "stateOfIncorporation": "DE",
  "stateOfIncorporationDescription": "DE",
  "fiscalYearEnd": "1231",
  "tickers": [
    "CNNE"
  ],
  "exchanges": [
    "NYSE"
  ],
  "ein": "821273460",
  "description": "",
  "website": "",
  "investorWebsite": "",
  "category": "Large accelerated filer",
  "phone": "702-323-7334",
  "flags": "",
  "formerNames": [],
  "filings_count": 598,
  "download_timestamp": "2025-08-02 07:21:18 UTC"
}