{
  "cik": "0001897532",
  "name": "Majestic Ideal Holdings Ltd",
  "entityType": "other",
  "sic": "2300",
  "sicDescription": "Apparel & Other Finishd Prods of  Fabrics & Similar Matl",
  "stateOfIncorporation": "E9",
  "stateOfIncorporationDescription": "Cayman Islands",
  "fiscalYearEnd": null,
  "tickers": [
    "MJID"
  ],
  "exchanges": [
    "Nasdaq"
  ],
  "ein": "000000000",
  "description": "",
  "website": "",
  "investorWebsite": "",
  "category": "",
  "phone": "852 9710 8044",
  "flags": "",
  "formerNames": [],
  "filings_count": 69,
  "download_timestamp": "2025-08-02 07:29:04 UTC"
}